{
    "type": "object",
    "properties": {
        "resourceGroupName": {
            "required": true,
            "type": "string",
            "minLength": 1,
            "maxLength": 90,
            "pattern": "^[-\\w\\._\\(\\)]+[^\\.]$"
        },
        "domainName": {
            "required": true,
            "type": "string"
        },
        "name": {
            "required": true,
            "type": "string"
        },
        "subscriptionId": {
            "required": true,
            "type": "string"
        },
        "requestBody": {
            "allOf": [
                {
                    "description": "Azure proxy only resource. This resource is not tracked by Azure Resource Manager.",
                    "properties": {
                        "id": {
                            "description": "Resource Id.",
                            "readOnly": true,
                            "type": "string"
                        },
                        "kind": {
                            "description": "Kind of resource.",
                            "type": "string"
                        },
                        "name": {
                            "description": "Resource Name.",
                            "readOnly": true,
                            "type": "string"
                        },
                        "type": {
                            "description": "Resource type.",
                            "readOnly": true,
                            "type": "string"
                        }
                    },
                    "x-ms-azure-resource": true,
                    "type": "object"
                }
            ],
            "description": "Domain ownership Identifier.",
            "properties": {
                "properties": {
                    "description": "DomainOwnershipIdentifier resource specific properties",
                    "properties": {
                        "ownershipId": {
                            "description": "Ownership Id.",
                            "type": "string"
                        }
                    },
                    "x-ms-client-flatten": true
                }
            },
            "type": "object"
        },
        "api_version": {
            "required": true,
            "type": "string"
        }
    }
}